{
    "timeline":
    {
        "headline":"Indy Tech Week 2012",
        "type":"default",
        "text":"<p>Indy Tech Week is an umbrella label for several really cool business and tech related events, conferences and more going on in Indianapolis.</p>",
        "asset": {
            "media":"http://yourdomain_or_socialmedialink_goes_here.jpg",
            "credit":"Sponsored by",
            "caption":"ExactTarget, re:build, Verge"
        },
        "date": [
            {
                "startDate":"2012,10,11",
                "endDate":"2012,10,11",
                "headline":"re:build 2012<br />Pre-party and VIP Dinner",
                "text":"<p></p>",
                "tag":"re:build",
                "asset": {
                    "thumbnail":"/img/rebuild-icon.png",
                    "credit":"Sponsored by",
                    "caption":"Talentopoly &amp; JSMeetup"
                }
            },
            {
                "startDate":"2012,10,12",
                "endDate":"2012,10,12",
                "headline":"re:build Conference",
                "text":"<p>The official re:build conference for 2012</p>",
                "tag":"re:build",
                "asset": {
                    "media":"https://twitter.com/rebuildconf/status/244152045408505856",
                    "thumbnail":"optional-32x32px.jpg",
                    "credit":"Sponsored by",
                    "caption":"JSMeetup"
                }
            },
            {
                "startDate":"2012,10,13",
                "endDate":"2012,10,13",
                "headline":"Broad Ripple Music Festival",
                "text":"<p>The Sixth annual Broad Ripple Music Fest will invade Indy's favorite cultural community mecca on Saturday, October 13th.</p>",
                "tag":"Indy Tech Week",
                "asset": {
                    "media":"http://www.youtube.com/watch?feature=player_embedded&v=PpAnF9Mzb7k",
                    "thumbnail":"optional-32x32px.jpg",
                    "credit":"Sponsored By",
                    "caption":"Upland Brewing Co., Butler Scion, PrintResources, PRN Graphics, PBR, NUVO, Kolman, SmallBox, 92.3 WTTS, SquareJive, AyoKay, DO317, indyPride, yelp, the Onion"
                }
            },
            {
                "startDate":"2012,10,14",
                "endDate":"2012,10,14",
                "headline":"Indy Hack Day",
                "text":"<p>A full-on hackathon, giving you the chance to earn some street cred!!!</p>",
                "tag":"Verge",
                "asset": {
                    "media":"http://3.bp.blogspot.com/-kBAD-154uHk/UFCT6YO6j-I/AAAAAAAAAGs/qKA6pgBGSn8/s1600/IndyHack.png",
                    "thumbnail":"optional-32x32px.jpg",
                    "credit":"Sponsored By",
                    "caption":"Verge &amp; Talentopoly"
                }
            },
            {
                "startDate":"2012,10,15",
                "endDate":"2012,10,15",
                "headline":"Geek Power Ride",
                "text":"<p>Tag yourself with your corporate t-shirt, hop on your bike and hit the monon with the locals!</p>",
                "tag":"Indy Tech Week",
                "asset": {
                    "thumbnail":"optional-32x32px.jpg",
                    "credit":"Sponsored By",
                    "caption":"Verge, re:build and you??"
                }
            },
            {
                "startDate":"2012,10,16",
                "endDate":"2012,10,18",
                "headline":"Connections 2012",
                "text":"<p>At ExactTarget, we believe each individual has the power to Inspire the Future. Through more than 40 breakout sessions, we’ll explore how inspiration comes to life—fueling creativity, improving communities, and building businesses—sparking innovation for years to come.</p>",
                "tag":"ExactTarget",
                "asset": {
                    "media":"http://www.youtube.com/watch?feature=player_embedded&v=Dh0gzSOzKrU",
                    "thumbnail":"optional-32x32px.jpg",
                    "credit":"Sponsored By",
                    "caption":"ExactTarget"
                }
            },
            {
                "startDate":"2012,10,17",
                "endDate":"2012,10,19",
                "headline":"Powder Keg",
                "text":"<p>Experience 2 1/2 days of engaged learning and vantage-shifting inspiration. Connect with a group of exceptional entrepreneurs, developers, and creatives.</p>",
                "tag":"Verge",
                "asset": {
                    "media":"https://twitter.com/PowderKegConf/status/240783100152516609",
                    "thumbnail":"optional-32x32px.jpg",
                    "credit":"Sponsored By",
                    "caption":"Verge"
                }
            }
        ],
        "era": [
            {
                "startDate":"2012,10,10",
                "endDate":"2012,10,20",
                "headline":"Indy Tech Week",
                "text":"<p>So Cool</p>",
                "tag":"Indy Tech Week"
            }
        ]
    }
}
